{"output": {"keypoints": [{"y": 328, "x": 423}, {"y": 347, "x": 609}, {"y": 159, "x": 746}, {"y": 138, "x": 663}, {"y": 113, "x": 583}, {"y": 143, "x": 412}, {"y": 48, "x": 460}, {"y": 331.0, "x": 414.0}, {"y": 334.0, "x": 452.0}, {"y": 329.0, "x": 431.0}, {"y": 270.0, "x": 685.0}, {"y": 305.0, "x": 656.0}, {"y": 322.0, "x": 624.0}, {"y": 344.0, "x": 588.0}, {"y": 386.0, "x": 543.0}, {"y": 410.0, "x": 516.0}, {"y": 422.0, "x": 525.0}, {"y": 423.0, "x": 549.0}, {"y": 417.0, "x": 558.0}, {"y": 351.0, "x": 626.0}, {"y": 310.0, "x": 662.0}, {"y": 261.0, "x": 714.0}, {"y": 146.0, "x": 728.0}, {"y": 153.0, "x": 714.0}, {"y": 170.0, "x": 770.0}, {"y": 151.0, "x": 776.0}, {"y": 157.0, "x": 759.0}, {"y": 145.0, "x": 733.0}, {"y": 128.0, "x": 657.0}, {"y": 138.0, "x": 627.0}, {"y": 141.0, "x": 658.0}, {"y": 149.0, "x": 689.0}, {"y": 121.0, "x": 659.0}, {"y": 128.0, "x": 587.0}, {"y": 137.0, "x": 621.0}, {"y": 130.0, "x": 610.0}, {"y": 101.0, "x": 592.0}, {"y": 77.0, "x": 434.0}, {"y": 93.0, "x": 346.0}, {"y": 115.0, "x": 341.0}, {"y": 195.0, "x": 324.0}, {"y": 228.0, "x": 357.0}, {"y": 242.0, "x": 376.0}, {"y": 254.0, "x": 389.0}, {"y": 242.0, "x": 412.0}, {"y": 238.0, "x": 419.0}, {"y": 234.0, "x": 400.0}, {"y": 218.0, "x": 416.0}, {"y": 212.0, "x": 390.0}, {"y": 191.0, "x": 411.0}, {"y": 180.0, "x": 393.0}, {"y": 174.0, "x": 414.0}, {"y": 165.0, "x": 414.0}, {"y": 162.0, "x": 491.0}, {"y": 138.0, "x": 531.0}, {"y": 102.0, "x": 504.0}, {"y": 91.0, "x": 508.0}, {"y": 87.0, "x": 491.0}, {"y": 71.0, "x": 504.0}, {"y": 51.0, "x": 446.0}, {"y": 47.0, "x": 481.0}]}}